i18n_check/__init__.py
i18n_check/utils.py
i18n_check/check/__init__.py
i18n_check/check/all_checks.py
i18n_check/check/alt_texts.py
i18n_check/check/aria_labels.py
i18n_check/check/key_formatting.py
i18n_check/check/key_naming.py
i18n_check/check/missing_keys.py
i18n_check/check/nested_files.py
i18n_check/check/non_source_keys.py
i18n_check/check/nonexistent_keys.py
i18n_check/check/repeat_keys.py
i18n_check/check/repeat_values.py
i18n_check/check/sorted_keys.py
i18n_check/check/unused_keys.py
i18n_check/cli/__init__.py
i18n_check/cli/generate_config_file.py
i18n_check/cli/generate_test_frontends.py
i18n_check/cli/main.py
i18n_check/cli/upgrade.py
i18n_check/cli/version.py
i18n_check/test_frontends/all_checks_fail/test_file.ts
i18n_check/test_frontends/all_checks_fail/skip_dir/skip_test_file.ts
i18n_check/test_frontends/all_checks_fail/sub_dir/sub_dir_first_file.ts
i18n_check/test_frontends/all_checks_fail/sub_dir/sub_dir_second_file.ts
i18n_check/test_frontends/all_checks_fail/test_i18n/test_i18n_locale.json
i18n_check/test_frontends/all_checks_fail/test_i18n/test_i18n_src.json
i18n_check/test_frontends/all_checks_pass/test_file.ts
i18n_check/test_frontends/all_checks_pass/sub_dir/sub_dir_first_file.ts
i18n_check/test_frontends/all_checks_pass/sub_dir/sub_dir_second_file.ts
i18n_check/test_frontends/all_checks_pass/test_i18n/test_i18n_locale.json
i18n_check/test_frontends/all_checks_pass/test_i18n/test_i18n_src.json
i18n_check-1.18.0.dist-info/licenses/LICENSE.txt
i18n_check-1.18.0.dist-info/METADATA
i18n_check-1.18.0.dist-info/WHEEL
i18n_check-1.18.0.dist-info/entry_points.txt
i18n_check-1.18.0.dist-info/top_level.txt
i18n_check-1.18.0.dist-info/RECORD
