Metadata-Version: 2.4
Name: i18n-check
Version: 1.18.0
Summary: Check i18n/L10n keys and values
Author-email: i18n-check developers <engineering@activist.org>
Project-URL: Homepage, https://github.com/activist-org/i18n-check
Keywords: i18n,l10n,internationalization,localization,ci,cli
Classifier: Development Status :: 5 - Production/Stable
Classifier: Intended Audience :: Developers
Classifier: Topic :: Software Development :: Internationalization
Classifier: Topic :: Software Development :: Localization
Classifier: License :: OSI Approved :: GNU General Public License v3 (GPLv3)
Classifier: Programming Language :: Python
Classifier: Programming Language :: Python :: 3
Classifier: Programming Language :: Python :: 3.12
Classifier: Programming Language :: Python :: 3.13
Classifier: Programming Language :: Python :: 3.14
Classifier: Operating System :: OS Independent
Requires-Python: >=3.12
License-File: LICENSE.txt
Requires-Dist: packaging>=26.0
Requires-Dist: pyyaml>=6.0.3
Requires-Dist: requests>=2.32.5
Requires-Dist: rich>=14.2.0
Provides-Extra: dev
Requires-Dist: mypy>=1.19.1; extra == "dev"
Requires-Dist: pre-commit>=4.5.1; extra == "dev"
Requires-Dist: pytest>=9.0.2; extra == "dev"
Requires-Dist: pytest-cov>=7.0.0; extra == "dev"
Requires-Dist: ruff>=0.14.14; extra == "dev"
Requires-Dist: setuptools>=80.10.1; extra == "dev"
Requires-Dist: types-PyYAML>=6.0.12.20250915; extra == "dev"
Requires-Dist: types-requests>=2.32.4.20260107; extra == "dev"
Provides-Extra: docs
Requires-Dist: m2r2>=0.3.0; extra == "docs"
Requires-Dist: numpydoc>=1.10.0; extra == "docs"
Requires-Dist: sphinx-rtd-theme>=3.1.0; extra == "docs"
Dynamic: license-file
